easysnmptable/__init__.py
easysnmptable/session.py
easysnmptable/table.py
easysnmptable-0.1.1.dist-info/DESCRIPTION.rst
easysnmptable-0.1.1.dist-info/METADATA
easysnmptable-0.1.1.dist-info/RECORD
easysnmptable-0.1.1.dist-info/WHEEL
easysnmptable-0.1.1.dist-info/metadata.json
easysnmptable-0.1.1.dist-info/top_level.txt
