Metadata-Version: 2.0
Name: easysnmptable
Version: 0.1.1
Summary: An extension to easysnmp providing table handling and other features.
Home-page: https://github.com/wolcomm/easysnmptable
Author: Workonline Communications
Author-email: communications@workonkonline.co.za
License: Apache-2.0
Download-URL: https://github.com/easysnmptable/0.1.1
Platform: UNKNOWN
Classifier: Development Status :: 4 - Beta
Classifier: Intended Audience :: Developers
Classifier: License :: OSI Approved :: Apache Software License
Classifier: Topic :: Software Development :: Libraries :: Python Modules
Classifier: Topic :: Internet
Requires-Dist: easysnmp (<0.3,>=0.2.5)
